ai_coscientist/__init__.py
ai_coscientist/main.py
ai_coscientist-1.0.0.dist-info/LICENSE
ai_coscientist-1.0.0.dist-info/METADATA
ai_coscientist-1.0.0.dist-info/WHEEL
ai_coscientist-1.0.0.dist-info/RECORD
