Metadata-Version: 2.3
Name: ai-coscientist
Version: 1.0.0
Summary: A multi-agent AI framework for collaborative scientific research, implementing tournament-based hypothesis evolution and peer review systems
License: MIT
Keywords: artificial intelligence,multi-agent systems,scientific research,hypothesis generation,peer review,tournament selection,ai co-scientist
Author: The Swarm Corporation
Author-email: kye@swarms.world
Requires-Python: >=3.10,<4.0
Classifier: Development Status :: 4 - Beta
Classifier: Intended Audience :: Developers
Classifier: Intended Audience :: Science/Research
Classifier: License :: OSI Approved :: MIT License
Classifier: Programming Language :: Python :: 3
Classifier: Programming Language :: Python :: 3.10
Classifier: Programming Language :: Python :: 3.11
Classifier: Programming Language :: Python :: 3.12
Classifier: Programming Language :: Python :: 3.13
Classifier: Topic :: Scientific/Engineering
Classifier: Topic :: Scientific/Engineering :: Artificial Intelligence
Requires-Dist: loguru
Requires-Dist: python-dotenv
Requires-Dist: swarms
Project-URL: Documentation, https://github.com/The-Swarm-Corporation/AI-CoScientist/blob/main/DOCS.md
Project-URL: Homepage, https://github.com/The-Swarm-Corporation/AI-CoScientist
Project-URL: Repository, https://github.com/The-Swarm-Corporation/AI-CoScientist
